{
  "electoralDistrictNumber": "35040",
  "englishDistrictName": "\"Huron--Bruce\"",
  "frenchDistrictName": "\"Huron--Bruce\"",
  "\"NDP-New Democratic Party\"": {
    "familyName": "\"Creces\"",
    "middleName": "\"\"",
    "firstName": "\"Gerard\"",
    "votes": 7544
  },
  "\"Conservative\"": {
    "familyName": "\"Lobb\"",
    "middleName": "\"\"",
    "firstName": "\"Ben\"",
    "votes": 26174
  },
  "\"Green Party\"": {
    "familyName": "\"Splettstoesser\"",
    "middleName": "\"\"",
    "firstName": "\"Jutta\"",
    "votes": 1398
  },
  "\"Liberal\"": {
    "familyName": "\"Thompson\"",
    "middleName": "\"\"",
    "firstName": "\"Allan\"",
    "votes": 23129
  },
  "undefined": {
    "votes": null
  }
}