{
  "electoralDistrictNumber": "12006",
  "englishDistrictName": "\"Halifax West\"",
  "frenchDistrictName": "\"Halifax-Ouest\"",
  "\"NDP-New Democratic Party\"": {
    "familyName": "\"Hussey\"",
    "middleName": "\"\"",
    "firstName": "\"Joanne\"",
    "votes": 5894
  },
  "\"Conservative\"": {
    "familyName": "\"McGinnis\"",
    "middleName": "\"\"",
    "firstName": "\"Michael\"",
    "votes": 7837
  },
  "\"Liberal\"": {
    "familyName": "\"Regan\"",
    "middleName": "\"\"",
    "firstName": "\"Geoff\"",
    "votes": 34377
  },
  "\"Green Party\"": {
    "familyName": "\"Zurawski\"",
    "middleName": "\"\"",
    "firstName": "\"Richard Henryk\"",
    "votes": 1971
  },
  "undefined": {
    "votes": null
  }
}