{
  "electoralDistrictNumber": "24069",
  "englishDistrictName": "\"Saint-Léonard--Saint-Michel\"",
  "frenchDistrictName": "\"Saint-Léonard--Saint-Michel\"",
  "\"Liberal\"": {
    "familyName": "\"Di Iorio\"",
    "middleName": "\"\"",
    "firstName": "\"Nicola\"",
    "votes": 28826
  },
  "\"NDP-New Democratic Party\"": {
    "familyName": "\"Filato\"",
    "middleName": "\"\"",
    "firstName": "\"Rosannie\"",
    "votes": 6611
  },
  "\"Conservative\"": {
    "familyName": "\"Fournier\"",
    "middleName": "\"\"",
    "firstName": "\"Jean Philippe\"",
    "votes": 4957
  },
  "\"Bloc Québécois\"": {
    "familyName": "\"Gendron\"",
    "middleName": "\"\"",
    "firstName": "\"Steeve\"",
    "votes": 3204
  },
  "\"Marxist-Leninist\"": {
    "familyName": "\"Malek\"",
    "middleName": "\"\"",
    "firstName": "\"Arezki\"",
    "votes": 128
  },
  "\"Green Party\"": {
    "familyName": "\"Miscione\"",
    "middleName": "\"\"",
    "firstName": "\"Melissa\"",
    "votes": 805
  },
  "undefined": {
    "votes": null
  }
}