{
  "electoralDistrictNumber": "24016",
  "englishDistrictName": "\"Brome--Missisquoi\"",
  "frenchDistrictName": "\"Brome--Missisquoi\"",
  "\"NDP-New Democratic Party\"": {
    "familyName": "\"Lusson\"",
    "middleName": "\"\"",
    "firstName": "\"Catherine\"",
    "votes": 14383
  },
  "\"Bloc Québécois\"": {
    "familyName": "\"Melchior\"",
    "middleName": "\"\"",
    "firstName": "\"Patrick\"",
    "votes": 10252
  },
  "\"Green Party\"": {
    "familyName": "\"Moynan\"",
    "middleName": "\"\"",
    "firstName": "\"Cindy\"",
    "votes": 1377
  },
  "\"Forces et Démocratie - Allier les forces de nos régions\"": {
    "familyName": "\"Paine\"",
    "middleName": "\"\"",
    "firstName": "\"Patrick\"",
    "votes": 195
  },
  "\"Liberal\"": {
    "familyName": "\"Paradis\"",
    "middleName": "\"\"",
    "firstName": "\"Denis\"",
    "votes": 25744
  },
  "\"Conservative\"": {
    "familyName": "\"Poulin\"",
    "middleName": "\"\"",
    "firstName": "\"Charles\"",
    "votes": 6724
  },
  "undefined": {
    "votes": null
  }
}