{
  "electoralDistrictNumber": "35057",
  "englishDistrictName": "Milton",
  "frenchDistrictName": "Milton",
  "NDP-New Democratic Party": {
    "votes": 5366,
    "familyName": "Anabusi",
    "middleName": "",
    "firstName": "Alex"
  },
  "Green Party": {
    "votes": 1131,
    "familyName": "Batra",
    "middleName": "",
    "firstName": "Mini"
  },
  "Libertarian": {
    "votes": 493,
    "familyName": "Jewell",
    "middleName": "",
    "firstName": "Chris"
  },
  "Conservative": {
    "votes": 22378,
    "familyName": "Raitt",
    "middleName": "",
    "firstName": "Lisa"
  },
  "Liberal": {
    "votes": 19940,
    "familyName": "Rizvee",
    "middleName": "",
    "firstName": "Azim"
  }
}