{
  "electoralDistrictNumber": "24019",
  "englishDistrictName": "Charlesbourg--Haute-Saint-Charles",
  "frenchDistrictName": "Charlesbourg--Haute-Saint-Charles",
  "Green Party": {
    "votes": 1256,
    "familyName": "Baudet",
    "middleName": "",
    "firstName": "Nathalie"
  },
  "Liberal": {
    "votes": 13525,
    "familyName": "Côté",
    "middleName": "",
    "firstName": "Jean"
  },
  "NDP-New Democratic Party": {
    "votes": 11690,
    "familyName": "Day",
    "middleName": "",
    "firstName": "Anne-Marie"
  },
  "Conservative": {
    "votes": 24608,
    "familyName": "Paul-Hus",
    "middleName": "",
    "firstName": "Pierre"
  },
  "Bloc Québécois": {
    "votes": 7177,
    "familyName": "Turmel",
    "middleName": "",
    "firstName": "Marc Antoine"
  }
}