{
  "electoralDistrictNumber": "48022",
  "englishDistrictName": "Foothills",
  "frenchDistrictName": "Foothills",
  "Conservative": {
    "votes": 46166,
    "familyName": "Barlow",
    "middleName": "",
    "firstName": "John"
  },
  "Liberal": {
    "votes": 8149,
    "familyName": "MacPherson",
    "middleName": "",
    "firstName": "Tanya"
  },
  "Libertarian": {
    "votes": 424,
    "familyName": "Morgan",
    "middleName": "",
    "firstName": "Cory"
  },
  "Christian Heritage Party": {
    "votes": 345,
    "familyName": "Slingerland",
    "middleName": "",
    "firstName": "Marc"
  },
  "NDP-New Democratic Party": {
    "votes": 3919,
    "familyName": "Thompson",
    "middleName": "",
    "firstName": "Alison"
  },
  "Green Party": {
    "votes": 1983,
    "familyName": "Tittel",
    "middleName": "",
    "firstName": "Romy S."
  }
}