{
  "electoralDistrictNumber": "46002",
  "englishDistrictName": "Charleswood--St. James--Assiniboia--Headingley",
  "frenchDistrictName": "Charleswood--St. James--Assiniboia--Headingley",
  "Liberal": {
    "votes": 24531,
    "familyName": "Eyolfson",
    "middleName": "",
    "firstName": "Doug"
  },
  "Conservative": {
    "votes": 18408,
    "familyName": "Fletcher",
    "middleName": "",
    "firstName": "Steven"
  },
  "Green Party": {
    "votes": 1376,
    "familyName": "Nichols",
    "middleName": "",
    "firstName": "Kevin"
  },
  "NDP-New Democratic Party": {
    "votes": 2842,
    "familyName": "Paulley",
    "middleName": "",
    "firstName": "Tom"
  }
}